boto3_fs/__init__.py
boto3_fs/utils/Version.py
boto3_fs/utils/__init__.py
boto3_fs/version
boto3_fs-0.2.0.dist-info/LICENSE
boto3_fs-0.2.0.dist-info/METADATA
boto3_fs-0.2.0.dist-info/WHEEL
boto3_fs-0.2.0.dist-info/RECORD
