Metadata-Version: 2.3
Name: boto3_fs
Version: 0.2.0
Summary: Boto3-FS
License: Apache 2.0
Author: Dinis Cruz
Author-email: dinis.cruz@owasp.org
Requires-Python: >=3.12,<4.0
Classifier: License :: Other/Proprietary License
Classifier: Programming Language :: Python :: 3
Classifier: Programming Language :: Python :: 3.12
Classifier: Programming Language :: Python :: 3.13
Requires-Dist: osbot-utils
Project-URL: Homepage, https://github.com/owasp-sbot/Boto3-FS
Project-URL: Repository, https://github.com/owasp-sbot/Boto3-FS
